deepgram_captions/__init__.py
deepgram_captions/_version.py
deepgram_captions/converters.py
deepgram_captions/helpers.py
deepgram_captions/srt.py
deepgram_captions/webvtt.py
deepgram_captions-1.2.0.dist-info/LICENSE
deepgram_captions-1.2.0.dist-info/METADATA
deepgram_captions-1.2.0.dist-info/WHEEL
deepgram_captions-1.2.0.dist-info/top_level.txt
deepgram_captions-1.2.0.dist-info/RECORD
