Metadata-Version: 2.1
Name: deepgram-captions
Version: 1.2.0
Summary: A Python package for generating captions.
Home-page: https://github.com/deepgram/deepgram-python-captions
Author: Deepgram
Author-email: devrel@deepgram.com
Keywords: deepgram,captions,srt,webvtt
Classifier: Development Status :: 3 - Alpha
Classifier: Intended Audience :: Developers
Classifier: License :: OSI Approved :: MIT License
Classifier: Programming Language :: Python :: 3
Classifier: Programming Language :: Python :: 3 :: Only
Classifier: Topic :: Multimedia :: Sound/Audio :: Speech
Classifier: Topic :: Text Processing :: General
License-File: LICENSE
Provides-Extra: dev
Requires-Dist: black ; extra == 'dev'
Requires-Dist: pytest ; extra == 'dev'
